pya2l/__init__.py
pya2l/cli.py
pya2l/cli_test.py
pya2l/helpers_test.py
pya2l/md_test.py
pya2l/parser.py
pya2l/parser_test.py
pya2l/regression_test.py
pya2l/a2l_grpc/a2l_grpc_darwin_arm64.dylib
pya2l/a2l_grpc/a2l_grpc_darwin_arm64.h
pya2l/a2l_grpc/a2l_grpc_linux_386.h
pya2l/a2l_grpc/a2l_grpc_linux_386.so
pya2l/a2l_grpc/a2l_grpc_linux_amd64.h
pya2l/a2l_grpc/a2l_grpc_linux_amd64.so
pya2l/a2l_grpc/a2l_grpc_linux_arm.h
pya2l/a2l_grpc/a2l_grpc_linux_arm.so
pya2l/a2l_grpc/a2l_grpc_linux_arm64.h
pya2l/a2l_grpc/a2l_grpc_linux_arm64.so
pya2l/a2l_grpc/a2l_grpc_windows_386.dll
pya2l/a2l_grpc/a2l_grpc_windows_386.h
pya2l/a2l_grpc/a2l_grpc_windows_amd64.dll
pya2l/a2l_grpc/a2l_grpc_windows_amd64.h
pya2l/helpers/__init__.py
pya2l/helpers/axis_descr.py
pya2l/helpers/axis_pts.py
pya2l/helpers/characteristic.py
pya2l/helpers/compu_method.py
pya2l/helpers/helpers.py
pya2l/helpers/module.py
pya2l/helpers/record_layout.py
pya2l/helpers/referencer.py
pya2l/protobuf/A2L_pb2.py
pya2l/protobuf/A2L_pb2.pyi
pya2l/protobuf/A2L_pb2_grpc.py
pya2l/protobuf/A2ML_pb2.py
pya2l/protobuf/A2ML_pb2.pyi
pya2l/protobuf/A2ML_pb2_grpc.py
pya2l/protobuf/API_pb2.py
pya2l/protobuf/API_pb2.pyi
pya2l/protobuf/API_pb2_grpc.py
pya2l/protobuf/IF_DATA_pb2.py
pya2l/protobuf/IF_DATA_pb2.pyi
pya2l/protobuf/IF_DATA_pb2_grpc.py
pya2l/protobuf/shared_pb2.py
pya2l/protobuf/shared_pb2.pyi
pya2l/protobuf/shared_pb2_grpc.py
pya2l-0.1.10.dist-info/LICENSE.md
pya2l-0.1.10.dist-info/METADATA
pya2l-0.1.10.dist-info/WHEEL
pya2l-0.1.10.dist-info/entry_points.txt
pya2l-0.1.10.dist-info/top_level.txt
pya2l-0.1.10.dist-info/RECORD
