Metadata-Version: 2.2
Name: pya2l
Version: 0.1.10
Summary: utility for a2l files
Home-page: https://github.com/Sauci/pya2l
Author: Guillaume Sottas
Author-email: guillaumesottas@gmail.com
License: BSD License
Classifier: Programming Language :: Python :: 3
Classifier: License :: OSI Approved :: BSD License
Classifier: Operating System :: Microsoft :: Windows
Classifier: Operating System :: Unix
Requires-Python: >=3.9
License-File: LICENSE.md
Requires-Dist: grpcio>=1.71.0
Requires-Dist: grpcio-tools>=1.71.0
Requires-Dist: dictdiffer
